{"VERSION":"0.0.12","engineVersion":"","uuidToPath":{"12":{"12b137F-3bffe6I-ebbdd3L-170647E":{"path":".buildin/effect/Terrain3.pixel.hlsl","tempPath":"","mtime":1663412597477.7754,"meta":{"uuid":"12b137F-3bffe6I-ebbdd3L-170647E","importSettings":{},"dependencies":[],"fileDependencies":[]}},"1245faF-1a99c0I-04f0e6L-733300E":{"path":"Sprites/Background/bg3.jpg","tempPath":"","mtime":1589078554000,"meta":{"uuid":"1245faF-1a99c0I-04f0e6L-733300E","importSettings":{},"dependencies":[],"fileDependencies":[]}}},"13":{"13087dR-6d4ba4E-b482a5S-4bcabdR":{"path":"Scripts/MatchRoom.ts","tempPath":"","mtime":1664707706607.0325,"meta":{"uuid":"13087dR-6d4ba4E-b482a5S-4bcabdR","importSettings":{},"dependencies":[],"fileDependencies":[]}}},"14":{"140735F-701da6I-d53b73L-fc71caE":{"path":"Sprites/Poker/26.png","tempPath":"","mtime":1664246439694.5735,"meta":{"uuid":"140735F-701da6I-d53b73L-fc71caE","importSettings":{},"dependencies":[],"fileDependencies":[]}}},"16":{"160db9F-032ec7I-4d1176L-a20be7E":{"path":".buildin/effect/FXAA.pixel.hlsl","tempPath":"","mtime":1663412596159.3323,"meta":{"uuid":"160db9F-032ec7I-4d1176L-a20be7E","importSettings":{},"dependencies":[],"fileDependencies":[]}},"169c2bF-3549abI-a97599L-88b748E":{"path":"Sprites/Poker/15.png","tempPath":"","mtime":1664246439716.5151,"meta":{"uuid":"169c2bF-3549abI-a97599L-88b748E","importSettings":{},"dependencies":[],"fileDependencies":[]}}},"17":{"1740d7R-c7fa0eE-f38cd8S-91f8bbR":{"path":".buildin/Editor/loadingScene/script/loadMainScenes.ts","tempPath":"","mtime":1663412595621.7703,"meta":{"uuid":"1740d7R-c7fa0eE-f38cd8S-91f8bbR","importSettings":{},"dependencies":[],"fileDependencies":[]}}},"18":{"181059F-e98b05I-6a98b3L-6db287E":{"path":".buildin/Editor/defaultAssetsFiles/image.png","tempPath":"","mtime":1663412595511.067,"meta":{"uuid":"181059F-e98b05I-6a98b3L-6db287E","importSettings":{},"dependencies":[],"fileDependencies":[]}},"187926F-c5aa3dI-9ec358L-82bb59E":{"path":"Sprites/Button/join_room.png","tempPath":"","mtime":1649518376972.2102,"meta":{"uuid":"187926F-c5aa3dI-9ec358L-82bb59E","importSettings":{},"dependencies":[],"fileDependencies":[]}},"18c5c4R-ca6eaaE-e109b6S-6fef02R":{"path":"Scripts/PlayerBankerCard.ts","tempPath":"","mtime":1665316833130.406,"meta":{"uuid":"18c5c4R-ca6eaaE-e109b6S-6fef02R","importSettings":{},"dependencies":[],"fileDependencies":[]}}},"20":{"201ac0F-098ccdI-8f1083L-6829b1E":{"path":".buildin/effect/BloomThreshold.pixel.hlsl","tempPath":"","mtime":1663412595782.3416,"meta":{"uuid":"201ac0F-098ccdI-8f1083L-6829b1E","importSettings":{},"dependencies":[],"fileDependencies":[]}},"20cf78F-23028cI-6b51aaL-7ce02cE":{"path":".buildin/Editor/billboardImage/camera.png","tempPath":"","mtime":1663412595335.5354,"meta":{"uuid":"20cf78F-23028cI-6b51aaL-7ce02cE","importSettings":{},"dependencies":[],"fileDependencies":[]}},"20c057R-76a4feE-dbf72bS-5b3ea3R":{"path":".buildin/material/BlinnPhongMaterial.mat","tempPath":"","mtime":1663412597899.6052,"meta":{"uuid":"20c057R-76a4feE-dbf72bS-5b3ea3R","importSettings":{},"dependencies":[],"fileDependencies":[]}}},"21":{"2100b8R-0fc01aE-456bdaS-8e5319R":{"path":".buildin/material/ParticleMaterial.mat","tempPath":"","mtime":1663412597910.5771,"meta":{"uuid":"2100b8R-0fc01aE-456bdaS-8e5319R","importSettings":{},"dependencies":[],"fileDependencies":[]}},"21be4eF-e58841I-e76b60L-004b54E":{"path":"Sprites/pass.png","tempPath":"","mtime":1664550145983.4546,"meta":{"uuid":"21be4eF-e58841I-e76b60L-004b54E","importSettings":{},"dependencies":[],"fileDependencies":[]}},"21c623R-9d634eE-995898S-271d38R":{"path":"Prefabs/Info.prefab","tempPath":"","mtime":1664699473014.8289,"meta":{"uuid":"21c623R-9d634eE-995898S-271d38R","importSettings":{},"dependencies":[],"fileDependencies":[]}}},"22":{"2235deF-be0340I-b65274L-5fdc18E":{"path":"Sprites/Poker/19.png","tempPath":"","mtime":1664246439718.5095,"meta":{"uuid":"2235deF-be0340I-b65274L-5fdc18E","importSettings":{},"dependencies":[],"fileDependencies":[]}}},"23":{"239f5fF-dd1a79I-683039L-23c745E":{"path":"Sprites/Poker/10.png","tempPath":"","mtime":1664246439687.5918,"meta":{"uuid":"239f5fF-dd1a79I-683039L-23c745E","importSettings":{},"dependencies":[],"fileDependencies":[]}}},"24":{"24293aF-d225b5I-b8a32dL-22e943E":{"path":".buildin/effect/UI3D.pixel.hlsl","tempPath":"","mtime":1663412597772.9463,"meta":{"uuid":"24293aF-d225b5I-b8a32dL-22e943E","importSettings":{},"dependencies":[],"fileDependencies":[]}},"24a63cR-300945E-84abdfS-e4f960R":{"path":"Sprites/Poker/poker.atlaspac","tempPath":"","mtime":1664247439590.0696,"meta":{"uuid":"24a63cR-300945E-84abdfS-e4f960R","importSettings":{},"dependencies":[],"fileDependencies":[]}}},"25":{"25fecaF-bafef4I-484dbbL-5bd46dE":{"path":"Sprites/test_card.png","tempPath":"","mtime":1651989798527.931,"meta":{"uuid":"25fecaF-bafef4I-484dbbL-5bd46dE","importSettings":{},"dependencies":[],"fileDependencies":[]}}},"26":{"2652dfF-f60091I-8f74ccL-3f1066E":{"path":".buildin/effect/StandardLitAdd.vertex.hlsl","tempPath":"","mtime":1663412597419.8896,"meta":{"uuid":"2652dfF-f60091I-8f74ccL-3f1066E","importSettings":{},"dependencies":[],"fileDependencies":[]}},"26f9cdF-7c7bedI-e2049bL-28a777E":{"path":"Sprites/avatar.png","tempPath":"","mtime":1647587983104.974,"meta":{"uuid":"26f9cdF-7c7bedI-e2049bL-28a777E","importSettings":{},"dependencies":[],"fileDependencies":[]}},"263b2dF-0a259bI-9023e9L-26a947E":{"path":"Sprites/Poker/36.png","tempPath":"","mtime":1664246439655.6814,"meta":{"uuid":"263b2dF-0a259bI-9023e9L-26a947E","importSettings":{},"dependencies":[],"fileDependencies":[]}}},"27":{"278964R-a53b6cE-e0514aS-3145baR":{"path":"Prefabs/Player.prefab","tempPath":"","mtime":1664707958868.5232,"meta":{"uuid":"278964R-a53b6cE-e0514aS-3145baR","importSettings":{},"dependencies":[],"fileDependencies":[]}}},"28":{"28f36aR-07dd6aE-02ad84S-c295ffR":{"path":"Prefabs/Clock.prefab","tempPath":"","mtime":1664622463394.4216,"meta":{"uuid":"28f36aR-07dd6aE-02ad84S-c295ffR","importSettings":{},"dependencies":[],"fileDependencies":[]}}},"29":{"2970f7F-773901I-6abbe7L-7d1832E":{"path":".buildin/Editor/billboardImage/audio-source.png","tempPath":"","mtime":1663412595329.5522,"meta":{"uuid":"2970f7F-773901I-6abbe7L-7d1832E","importSettings":{},"dependencies":[],"fileDependencies":[]}},"29d895F-7bde68I-d71a41L-f689b4E":{"path":".buildin/Editor/billboardImage/particle.png","tempPath":"","mtime":1663412595349.4983,"meta":{"uuid":"29d895F-7bde68I-d71a41L-f689b4E","importSettings":{},"dependencies":[],"fileDependencies":[]}}},"30":{"3063bfF-e4fb30I-012543L-97771aE":{"path":"Sprites/Poker/48.png","tempPath":"","mtime":1664246439661.6633,"meta":{"uuid":"3063bfF-e4fb30I-012543L-97771aE","importSettings":{},"dependencies":[],"fileDependencies":[]}},"3061fcR-4c22f3E-95eabaS-6ee851R":{"path":"Scripts/GlobalManager.ts","tempPath":"","mtime":1664779080296.9553,"meta":{"uuid":"3061fcR-4c22f3E-95eabaS-6ee851R","importSettings":{},"dependencies":[],"fileDependencies":[]}}},"31":{"310d79R-074296E-7f2ad0S-664e0cR":{"path":".buildin/mesh/Sphere.mesh","tempPath":"","mtime":1663412598110.0417,"meta":{"uuid":"310d79R-074296E-7f2ad0S-664e0cR","importSettings":{},"dependencies":[],"fileDependencies":[]}},"31cfa2F-df2588I-464f2bL-d34a84E":{"path":".buildin/skybox/default_skybox_bottom.png","tempPath":"","mtime":1663412598175.867,"meta":{"uuid":"31cfa2F-df2588I-464f2bL-d34a84E","importSettings":{},"dependencies":[],"fileDependencies":[]}}},"37":{"37f7c2F-352dd6I-0d1db0L-2dc46aE":{"path":".buildin/mesh/Sphere.mesh.bin","tempPath":"","mtime":1663412598116.0269,"meta":{"uuid":"37f7c2F-352dd6I-0d1db0L-2dc46aE","importSettings":{},"dependencies":[],"fileDependencies":[]}},"37adeeF-7fc0dfI-c47bd7L-ad4a7cE":{"path":"Sprites/Poker/14.png","tempPath":"","mtime":1664246439688.5894,"meta":{"uuid":"37adeeF-7fc0dfI-c47bd7L-ad4a7cE","importSettings":{},"dependencies":[],"fileDependencies":[]}}},"40":{"405eabR-ca288aE-5bf4f3S-3b3bd3R":{"path":".buildin/effect/Bloom.effect","tempPath":"","mtime":1663412595755.413,"meta":{"uuid":"405eabR-ca288aE-5bf4f3S-3b3bd3R","importSettings":{},"dependencies":[],"fileDependencies":[]}},"40a89aF-f9bd9bI-268a39L-26e8a9E":{"path":".buildin/ui/default_particle.png","tempPath":"","mtime":1663412598294.5498,"meta":{"uuid":"40a89aF-f9bd9bI-268a39L-26e8a9E","importSettings":{},"dependencies":[],"fileDependencies":[]}}},"41":{"416690F-0b976aI-71e7ceL-ef7277E":{"path":".buildin/mesh/Cone.mesh.bin","tempPath":"","mtime":1663412597986.3745,"meta":{"uuid":"416690F-0b976aI-71e7ceL-ef7277E","importSettings":{},"dependencies":[],"fileDependencies":[]}}},"42":{"4297abR-4706b7E-79b4ccS-d53d45R":{"path":"Scenes/Home.scene","tempPath":"","mtime":1663483895236.5842,"meta":{"uuid":"4297abR-4706b7E-79b4ccS-d53d45R","importSettings":{},"dependencies":[],"fileDependencies":[]}}},"43":{"432e21F-d2ef28I-81e650L-eb0f3bE":{"path":"Sprites/Button/change.png","tempPath":"","mtime":1665290584750.8164,"meta":{"uuid":"432e21F-d2ef28I-81e650L-eb0f3bE","importSettings":{},"dependencies":[],"fileDependencies":[]}}},"44":{"44e0e0R-db917aE-769d71S-5eff01R":{"path":".buildin/effect/StandardLit.effect","tempPath":"","mtime":1663412597299.2112,"meta":{"uuid":"44e0e0R-db917aE-769d71S-5eff01R","importSettings":{},"dependencies":[],"fileDependencies":[]}}},"46":{"4641e1F-18405cI-fd7c7fL-20aa6fE":{"path":".buildin/effect/ShowCubeMap.pixel.hlsl","tempPath":"","mtime":1663412597092.7627,"meta":{"uuid":"4641e1F-18405cI-fd7c7fL-20aa6fE","importSettings":{},"dependencies":[],"fileDependencies":[]}},"465520F-cbd163I-9912aeL-db037bE":{"path":".buildin/ui/buildin_default_image.png","tempPath":"","mtime":1663412598263.631,"meta":{"uuid":"465520F-cbd163I-9912aeL-db037bE","importSettings":{},"dependencies":[],"fileDependencies":[]}}},"47":{"479654F-e70e30I-4d6a67L-699eb3E":{"path":".buildin/effect/Skybox.pixel.hlsl","tempPath":"","mtime":1663412597248.348,"meta":{"uuid":"479654F-e70e30I-4d6a67L-699eb3E","importSettings":{},"dependencies":[],"fileDependencies":[]}}},"51":{"51a9d5F-67f917I-47f918L-993c09E":{"path":"Sprites/poker.png","tempPath":"","mtime":1651990809773.04,"meta":{"uuid":"51a9d5F-67f917I-47f918L-993c09E","importSettings":{},"dependencies":[],"fileDependencies":[]}},"5151d2F-feb9a6I-b6398cL-cd2455E":{"path":"Sprites/Button/quick_start.png","tempPath":"","mtime":1649518375272.7378,"meta":{"uuid":"5151d2F-feb9a6I-b6398cL-cd2455E","importSettings":{},"dependencies":[],"fileDependencies":[]}}},"52":{"52807bF-831a79I-592f4bL-a11f24E":{"path":".buildin/effect/Effect3D.vertex.hlsl","tempPath":"","mtime":1663412595835.1982,"meta":{"uuid":"52807bF-831a79I-592f4bL-a11f24E","importSettings":{},"dependencies":[],"fileDependencies":[]}}},"53":{"53e5a3F-002148I-809e73L-489b61E":{"path":"Sprites/Poker/13.png","tempPath":"","mtime":1664246439667.688,"meta":{"uuid":"53e5a3F-002148I-809e73L-489b61E","importSettings":{},"dependencies":[],"fileDependencies":[]}}},"54":{"544a21F-8c1f53I-84e460L-ab8133E":{"path":".buildin/effect/BlinnPhong.vertex.hlsl","tempPath":"","mtime":1663412595722.5002,"meta":{"uuid":"544a21F-8c1f53I-84e460L-ab8133E","importSettings":{},"dependencies":[],"fileDependencies":[]}}},"56":{"56db00R-957ee9E-4a214fS-5f7c9fR":{"path":"Scenes/Index.scene","tempPath":"","mtime":1664551036005.8933,"meta":{"uuid":"56db00R-957ee9E-4a214fS-5f7c9fR","importSettings":{},"dependencies":[],"fileDependencies":[]}}},"57":{"5703b8F-247d36I-4d6502L-7c4470E":{"path":".buildin/effect/StandardLit.pixel.hlsl","tempPath":"","mtime":1663412597328.1343,"meta":{"uuid":"5703b8F-247d36I-4d6502L-7c4470E","importSettings":{},"dependencies":[],"fileDependencies":[]}},"57d21aR-e9016eE-ab534aS-92e1afR":{"path":".buildin/Editor/defaultAssets/script.ts","tempPath":"","mtime":1663412595462.1958,"meta":{"uuid":"57d21aR-e9016eE-ab534aS-92e1afR","importSettings":{},"dependencies":[],"fileDependencies":[]}}},"58":{"58743eF-eafbd6I-7df63fL-36c9d9E":{"path":".buildin/skybox/default_skybox_top.png","tempPath":"","mtime":1663412598195.8127,"meta":{"uuid":"58743eF-eafbd6I-7df63fL-36c9d9E","importSettings":{},"dependencies":[],"fileDependencies":[]}}},"59":{"596e81F-ef7aceI-fcda4cL-2dd681E":{"path":".buildin/effect/Terrain4.vertex.hlsl","tempPath":"","mtime":1663412597607.3872,"meta":{"uuid":"596e81F-ef7aceI-fcda4cL-2dd681E","importSettings":{},"dependencies":[],"fileDependencies":[]}},"59478cF-2ab7d3I-07382cL-41d7acE":{"path":".buildin/mesh/Plane.mesh.bin","tempPath":"","mtime":1663412598047.2117,"meta":{"uuid":"59478cF-2ab7d3I-07382cL-41d7acE","importSettings":{},"dependencies":[],"fileDependencies":[]}}},"60":{"60f7e6F-63237dI-3fa01cL-5728e2E":{"path":".buildin/Editor/loadingScene/progressbar/resource/Progress_Bar.png","tempPath":"","mtime":1663412595578.884,"meta":{"uuid":"60f7e6F-63237dI-3fa01cL-5728e2E","importSettings":{},"dependencies":[],"fileDependencies":[]}},"60ac2fR-4fc9a5E-e1da69S-b05568R":{"path":"Scripts/Databus.ts","tempPath":"","mtime":1664778368588.1423,"meta":{"uuid":"60ac2fR-4fc9a5E-e1da69S-b05568R","importSettings":{},"dependencies":[],"fileDependencies":[]}}},"61":{"614accR-a4e877E-02be6dS-49ed8fR":{"path":"Scripts/MyHandCard.ts","tempPath":"","mtime":1664537243101.237,"meta":{"uuid":"614accR-a4e877E-02be6dS-49ed8fR","importSettings":{},"dependencies":[],"fileDependencies":[]}}},"62":{"6220efF-f23e75I-a4aab2L-4d228aE":{"path":".buildin/mesh/Quad.mesh.bin","tempPath":"","mtime":1663412598069.1516,"meta":{"uuid":"6220efF-f23e75I-a4aab2L-4d228aE","importSettings":{},"dependencies":[],"fileDependencies":[]}},"628c5cF-712caeI-864fdfL-273f33E":{"path":"Sprites/Poker/30.png","tempPath":"","mtime":1664246439695.5706,"meta":{"uuid":"628c5cF-712caeI-864fdfL-273f33E","importSettings":{},"dependencies":[],"fileDependencies":[]}}},"63":{"63ff44F-07af6bI-ef5b3bL-a37122E":{"path":".buildin/effect/ForwardLit/input.hlsl","tempPath":"","mtime":1663412595898.031,"meta":{"uuid":"63ff44F-07af6bI-ef5b3bL-a37122E","importSettings":{},"dependencies":[],"fileDependencies":[]}},"632f18R-e6aaaaE-5ff76dS-1eba6dR":{"path":".buildin/mesh/Cone.mesh","tempPath":"","mtime":1663412597981.3867,"meta":{"uuid":"632f18R-e6aaaaE-5ff76dS-1eba6dR","importSettings":{},"dependencies":[],"fileDependencies":[]}},"638c29F-9cd3acI-1b4f5dL-1e8a21E":{"path":"Sprites/Poker/40.png","tempPath":"","mtime":1664246439657.6729,"meta":{"uuid":"638c29F-9cd3acI-1b4f5dL-1e8a21E","importSettings":{},"dependencies":[],"fileDependencies":[]}}},"64":{"64f333R-f808c0E-90235cS-b6162dR":{"path":".buildin/Editor/defaultAssets/animatorcontroller.animatorcontroller","tempPath":"","mtime":1663412595384.4387,"meta":{"uuid":"64f333R-f808c0E-90235cS-b6162dR","importSettings":{},"dependencies":[],"fileDependencies":[]}}},"65":{"65d950F-914affI-8243e4L-ce8c47E":{"path":"Sprites/Poker/29.png","tempPath":"","mtime":1664246439675.624,"meta":{"uuid":"65d950F-914affI-8243e4L-ce8c47E","importSettings":{},"dependencies":[],"fileDependencies":[]}}},"67":{"67ca23F-27ca9eI-c8b9e9L-59f23bE":{"path":".buildin/effect/BlinnPhong.pixel.hlsl","tempPath":"","mtime":1663412595716.518,"meta":{"uuid":"67ca23F-27ca9eI-c8b9e9L-59f23bE","importSettings":{},"dependencies":[],"fileDependencies":[]}},"670061F-16217dI-d0ddc3L-67683fE":{"path":".buildin/effect/Simple3D.pixel.hlsl","tempPath":"","mtime":1663412597166.5652,"meta":{"uuid":"670061F-16217dI-d0ddc3L-67683fE","importSettings":{},"dependencies":[],"fileDependencies":[]}}},"69":{"69b50cR-079dd4E-c7a81fS-047831R":{"path":".buildin/mesh/Quad.mesh","tempPath":"","mtime":1663412598062.1697,"meta":{"uuid":"69b50cR-079dd4E-c7a81fS-047831R","importSettings":{},"dependencies":[],"fileDependencies":[]}},"69a35cF-43e68aI-a84c52L-b78656E":{"path":"Sprites/Poker/42.png","tempPath":"","mtime":1664246439701.5542,"meta":{"uuid":"69a35cF-43e68aI-a84c52L-b78656E","importSettings":{},"dependencies":[],"fileDependencies":[]}}},"70":{"7081eeF-a34052I-d28478L-a5c793E":{"path":".buildin/ui/buildin_default_button.png","tempPath":"","mtime":1663412598250.6665,"meta":{"uuid":"7081eeF-a34052I-d28478L-a5c793E","importSettings":{},"dependencies":[],"fileDependencies":[]}},"70f678R-b817d2E-a0e526S-96b08bR":{"path":".buildin/mesh/Plane.mesh","tempPath":"","mtime":1663412598042.2239,"meta":{"uuid":"70f678R-b817d2E-a0e526S-96b08bR","importSettings":{},"dependencies":[],"fileDependencies":[]}}},"73":{"73453aF-3db729I-a63c81L-c07398E":{"path":"Sprites/frame_plus.png","tempPath":"","mtime":1648962642687.5852,"meta":{"uuid":"73453aF-3db729I-a63c81L-c07398E","importSettings":{},"dependencies":[],"fileDependencies":[]}}},"74":{"74128cR-472a42E-07e50cS-fb90efR":{"path":".buildin/ui/buildin_transparent_spriteframe.spriteframe","tempPath":"","mtime":1663412598287.5688,"meta":{"uuid":"74128cR-472a42E-07e50cS-fb90efR","importSettings":{},"dependencies":[],"fileDependencies":[]}}},"76":{"769610R-923901E-302c63S-76c641R":{"path":".buildin/effect/Image2D.effect","tempPath":"","mtime":1663412596461.4521,"meta":{"uuid":"769610R-923901E-302c63S-76c641R","importSettings":{},"dependencies":[],"fileDependencies":[]}},"768310F-26ef5aI-185b26L-18c3d4E":{"path":"Sprites/Poker/1.png","tempPath":"","mtime":1664246439663.6555,"meta":{"uuid":"768310F-26ef5aI-185b26L-18c3d4E","importSettings":{},"dependencies":[],"fileDependencies":[]}}},"77":{"77a241F-f8d8c5I-935304L-647dc8E":{"path":".buildin/effect/StandardLitAdd.pixel.hlsl","tempPath":"","mtime":1663412597381.9905,"meta":{"uuid":"77a241F-f8d8c5I-935304L-647dc8E","importSettings":{},"dependencies":[],"fileDependencies":[]}}},"79":{"79bd11F-7a94b1I-02fba6L-7ef7f2E":{"path":".buildin/effect/GaussianBlurHorizontal.pixel.hlsl","tempPath":"","mtime":1663412596258.994,"meta":{"uuid":"79bd11F-7a94b1I-02fba6L-7ef7f2E","importSettings":{},"dependencies":[],"fileDependencies":[]}},"79b14cF-6fd47aI-66fb1cL-b7c0b7E":{"path":"Sprites/Poker/46.png","tempPath":"","mtime":1664246439703.5508,"meta":{"uuid":"79b14cF-6fd47aI-66fb1cL-b7c0b7E","importSettings":{},"dependencies":[],"fileDependencies":[]}}},"80":{"80f1c7F-c71e36I-18f4b0L-c048a2E":{"path":".buildin/effect/BlinnPhongAdd.pixel.hlsl","tempPath":"","mtime":1663412595732.4746,"meta":{"uuid":"80f1c7F-c71e36I-18f4b0L-c048a2E","importSettings":{},"dependencies":[],"fileDependencies":[]}},"807574R-a439d2E-63e6a6S-c095d8R":{"path":".buildin/material/Effec3DMaterial.mat","tempPath":"","mtime":1663412597905.59,"meta":{"uuid":"807574R-a439d2E-63e6a6S-c095d8R","importSettings":{},"dependencies":[],"fileDependencies":[]}}},"82":{"82499fR-1e14a2E-5009b5S-9f2e31R":{"path":".buildin/effect/Terrain4.effect","tempPath":"","mtime":1663412597543.5588,"meta":{"uuid":"82499fR-1e14a2E-5009b5S-9f2e31R","importSettings":{},"dependencies":[],"fileDependencies":[]}},"822a17R-a8d0cfE-45d126S-6f7b6bR":{"path":".buildin/effect/Text2D.effect","tempPath":"","mtime":1663412597641.2954,"meta":{"uuid":"822a17R-a8d0cfE-45d126S-6f7b6bR","importSettings":{},"dependencies":[],"fileDependencies":[]}}},"83":{"83166aR-5c1143E-08c90fS-aead97R":{"path":".buildin/Editor/defaultAssets/mesh.mesh","tempPath":"","mtime":1663412595420.308,"meta":{"uuid":"83166aR-5c1143E-08c90fS-aead97R","importSettings":{},"dependencies":[],"fileDependencies":[]}},"831a27F-7e0eecI-861946L-1efcd5E":{"path":"Sprites/Poker/34.png","tempPath":"","mtime":1664246439697.5654,"meta":{"uuid":"831a27F-7e0eecI-861946L-1efcd5E","importSettings":{},"dependencies":[],"fileDependencies":[]}}},"84":{"84d317F-027d41I-e72a3dL-155795E":{"path":".buildin/effect/StandardLit.vertex.hlsl","tempPath":"","mtime":1663412597356.0586,"meta":{"uuid":"84d317F-027d41I-e72a3dL-155795E","importSettings":{},"dependencies":[],"fileDependencies":[]}},"842370F-fe7034I-05731eL-fda734E":{"path":".buildin/effect/UI3D.vertex.hlsl","tempPath":"","mtime":1663412597811.8398,"meta":{"uuid":"842370F-fe7034I-05731eL-fda734E","importSettings":{},"dependencies":[],"fileDependencies":[]}}},"85":{"85b745R-645628E-dacec4S-2de877R":{"path":".buildin/Editor/tutorial/skybox-criterion.ts","tempPath":"","mtime":1663412595658.6719,"meta":{"uuid":"85b745R-645628E-dacec4S-2de877R","importSettings":{},"dependencies":[],"fileDependencies":[]}},"85ac24F-8dce81I-b8e99fL-4168f8E":{"path":".buildin/mesh/Capsule.mesh.bin","tempPath":"","mtime":1663412597971.4126,"meta":{"uuid":"85ac24F-8dce81I-b8e99fL-4168f8E","importSettings":{},"dependencies":[],"fileDependencies":[]}},"8558d7R-dbecfaE-07dcfaS-3f2347R":{"path":"Prefabs/ActionCard.prefab","tempPath":"","mtime":1664621599893.649,"meta":{"uuid":"8558d7R-dbecfaE-07dcfaS-3f2347R","importSettings":{},"dependencies":[],"fileDependencies":[]}}},"88":{"8882f4F-e40cdbI-e31484L-2054b7E":{"path":".buildin/effect/Effect3D.pixel.hlsl","tempPath":"","mtime":1663412595825.2266,"meta":{"uuid":"8882f4F-e40cdbI-e31484L-2054b7E","importSettings":{},"dependencies":[],"fileDependencies":[]}}},"89":{"892b21F-2b0a91I-ff31d6L-ff48e2E":{"path":".buildin/effect/Image2D.pixel.hlsl","tempPath":"","mtime":1663412596495.361,"meta":{"uuid":"892b21F-2b0a91I-ff31d6L-ff48e2E","importSettings":{},"dependencies":[],"fileDependencies":[]}},"89c5baF-86dd86I-6dcff2L-5a3c9bE":{"path":".buildin/effect/Terrain3.vertex.hlsl","tempPath":"","mtime":1663412597509.6477,"meta":{"uuid":"89c5baF-86dd86I-6dcff2L-5a3c9bE","importSettings":{},"dependencies":[],"fileDependencies":[]}}},"90":{"905543R-0f9469E-03f987S-a03f35R":{"path":".buildin/Editor/defaultAssets/avatar.avatar","tempPath":"","mtime":1663412595392.3835,"meta":{"uuid":"905543R-0f9469E-03f987S-a03f35R","importSettings":{},"dependencies":[],"fileDependencies":[]}},"9070d0R-6ecf49E-2fce37S-810555R":{"path":".buildin/mesh/Cube.mesh","tempPath":"","mtime":1663412597997.3433,"meta":{"uuid":"9070d0R-6ecf49E-2fce37S-810555R","importSettings":{},"dependencies":[],"fileDependencies":[]}}},"91":{"91082aF-280898I-471f87L-f54eb9E":{"path":"Sprites/Poker/47.png","tempPath":"","mtime":1664246439728.5166,"meta":{"uuid":"91082aF-280898I-471f87L-f54eb9E","importSettings":{},"dependencies":[],"fileDependencies":[]}}},"92":{"928f5eF-26eef4I-d31e53L-1ed517E":{"path":"Sprites/Poker/8.png","tempPath":"","mtime":1664246439641.715,"meta":{"uuid":"928f5eF-26eef4I-d31e53L-1ed517E","importSettings":{},"dependencies":[],"fileDependencies":[]}}},"93":{"935c59F-d4cf0bI-7dcb34L-a344c0E":{"path":"Sprites/Poker/27.png","tempPath":"","mtime":1664246439720.545,"meta":{"uuid":"935c59F-d4cf0bI-7dcb34L-a344c0E","importSettings":{},"dependencies":[],"fileDependencies":[]}}},"94":{"94e3d4F-a5435bI-1c0b82L-d0c94aE":{"path":"Sprites/Poker/5.png","tempPath":"","mtime":1664246439664.6538,"meta":{"uuid":"94e3d4F-a5435bI-1c0b82L-d0c94aE","importSettings":{},"dependencies":[],"fileDependencies":[]}}},"95":{"95537cF-163881I-bf69f0L-0c3747E":{"path":".buildin/effect/FastBloomResolve.pixel.hlsl","tempPath":"","mtime":1663412595866.117,"meta":{"uuid":"95537cF-163881I-bf69f0L-0c3747E","importSettings":{},"dependencies":[],"fileDependencies":[]}},"9507b5F-679b0aI-ef74caL-86a158E":{"path":".buildin/ui/buildin_transparent_image.png","tempPath":"","mtime":1663412598277.5947,"meta":{"uuid":"9507b5F-679b0aI-ef74caL-86a158E","importSettings":{},"dependencies":[],"fileDependencies":[]}},"95c2e0R-3b1531E-5fb9bfS-1e9682R":{"path":"Prefabs/Pass.prefab","tempPath":"","mtime":1664608841628.8308,"meta":{"uuid":"95c2e0R-3b1531E-5fb9bfS-1e9682R","importSettings":{},"dependencies":[],"fileDependencies":[]}}},"96":{"9647e1F-ef04f0I-5e055aL-7c36ffE":{"path":"Sprites/Poker/12.png","tempPath":"","mtime":1664246439643.709,"meta":{"uuid":"9647e1F-ef04f0I-5e055aL-7c36ffE","importSettings":{},"dependencies":[],"fileDependencies":[]}}},"99":{"998444R-4e8cd1E-52b60bS-d1c239R":{"path":".buildin/effect/Blit.effect","tempPath":"","mtime":1663412595747.4338,"meta":{"uuid":"998444R-4e8cd1E-52b60bS-d1c239R","importSettings":{},"dependencies":[],"fileDependencies":[]}}},"c7":{"c7fb21R-abb109E-a8e91bS-54b4baR":{"path":".buildin/effect/BlinnPhong.effect","tempPath":"","mtime":1663412595679.6157,"meta":{"uuid":"c7fb21R-abb109E-a8e91bS-54b4baR","importSettings":{},"dependencies":[],"fileDependencies":[]}},"c7aeb0F-19484dI-7c42e1L-d3e7a3E":{"path":"package-lock.json","tempPath":"","mtime":1663412576335.6072,"meta":{"uuid":"c7aeb0F-19484dI-7c42e1L-d3e7a3E","importSettings":{},"dependencies":[],"fileDependencies":[]}},"c727dcR-10847dE-3538a9S-34d4e4R":{"path":"Scripts/MyBattle.ts","tempPath":"","mtime":1665317806453.505,"meta":{"uuid":"c727dcR-10847dE-3538a9S-34d4e4R","importSettings":{},"dependencies":[],"fileDependencies":[]}}},"9c":{"9c3b78F-05cffcI-208849L-9d69bdE":{"path":".buildin/effect/BlinnPhongAdd.vertex.hlsl","tempPath":"","mtime":1663412595738.459,"meta":{"uuid":"9c3b78F-05cffcI-208849L-9d69bdE","importSettings":{},"dependencies":[],"fileDependencies":[]}},"9c5a7cR-297750E-02542fS-c46fe5R":{"path":".buildin/mesh/Capsule.mesh","tempPath":"","mtime":1663412597961.4392,"meta":{"uuid":"9c5a7cR-297750E-02542fS-c46fe5R","importSettings":{},"dependencies":[],"fileDependencies":[]}}},"7a":{"7abc38F-998669I-c6e768L-885077E":{"path":".buildin/effect/BloomBlit.pixel.hlsl","tempPath":"","mtime":1663412595765.386,"meta":{"uuid":"7abc38F-998669I-c6e768L-885077E","importSettings":{},"dependencies":[],"fileDependencies":[]}}},"fa":{"fa5214F-f144feI-b42925L-f634cdE":{"path":".buildin/effect/BoxSampling_0.pixel.hlsl","tempPath":"","mtime":1663412595792.3145,"meta":{"uuid":"fa5214F-f144feI-b42925L-f634cdE","importSettings":{},"dependencies":[],"fileDependencies":[]}}},"4d":{"4d75e4F-57d3a3I-50c7e4L-daad75E":{"path":".buildin/effect/BoxSampling_1.pixel.hlsl","tempPath":"","mtime":1663412595802.2883,"meta":{"uuid":"4d75e4F-57d3a3I-50c7e4L-daad75E","importSettings":{},"dependencies":[],"fileDependencies":[]}},"4d79b5R-77877bE-9c5d28S-e77040R":{"path":".buildin/skybox/default_skybox.mat","tempPath":"","mtime":1663412598207.781,"meta":{"uuid":"4d79b5R-77877bE-9c5d28S-e77040R","importSettings":{},"dependencies":[],"fileDependencies":[]}},"4d1da9F-f91a07I-19a0e1L-c24280E":{"path":"Sprites/Button/host.png","tempPath":"","mtime":1648962642686.5884,"meta":{"uuid":"4d1da9F-f91a07I-19a0e1L-c24280E","importSettings":{},"dependencies":[],"fileDependencies":[]}}},"f7":{"f75b6eR-26db4aE-74d251S-b121f3R":{"path":".buildin/effect/Effect3D.effect","tempPath":"","mtime":1663412595813.2588,"meta":{"uuid":"f75b6eR-26db4aE-74d251S-b121f3R","importSettings":{},"dependencies":[],"fileDependencies":[]}},"f78e92F-12bf1eI-395e51L-372ffcE":{"path":"Sprites/Background/bg4.png","tempPath":"","mtime":1651390932903.6096,"meta":{"uuid":"f78e92F-12bf1eI-395e51L-372ffcE","importSettings":{},"dependencies":[],"fileDependencies":[]}},"f78cadF-bad696I-8c97d9L-ce721bE":{"path":"Sprites/Poker/33.png","tempPath":"","mtime":1664246439676.6206,"meta":{"uuid":"f78cadF-bad696I-8c97d9L-ce721bE","importSettings":{},"dependencies":[],"fileDependencies":[]}},"f7b056F-63126eI-94a16cL-3d6b87E":{"path":"Sprites/card_back.png","tempPath":"","mtime":1664699311691.4724,"meta":{"uuid":"f7b056F-63126eI-94a16cL-3d6b87E","importSettings":{},"dependencies":[],"fileDependencies":[]}}},"a8":{"a89e58R-501dacE-58eef3S-f88a8dR":{"path":".buildin/effect/FXAA.effect","tempPath":"","mtime":1663412596089.5198,"meta":{"uuid":"a89e58R-501dacE-58eef3S-f88a8dR","importSettings":{},"dependencies":[],"fileDependencies":[]}},"a871aaF-ed6279I-d8058bL-d79f23E":{"path":"Sprites/Poker/50.png","tempPath":"","mtime":1664246439705.5444,"meta":{"uuid":"a871aaF-ed6279I-d8058bL-d79f23E","importSettings":{},"dependencies":[],"fileDependencies":[]}}},"f9":{"f973dfR-b74c58E-19a8a4S-8daee0R":{"path":".buildin/effect/FastBloom.effect","tempPath":"","mtime":1663412595848.1643,"meta":{"uuid":"f973dfR-b74c58E-19a8a4S-8daee0R","importSettings":{},"dependencies":[],"fileDependencies":[]}}},"9b":{"9b9e8bF-72cbd0I-4b6c6bL-01615eE":{"path":".buildin/effect/ForwardLit/lit.hlsl","tempPath":"","mtime":1663412595909.0024,"meta":{"uuid":"9b9e8bF-72cbd0I-4b6c6bL-01615eE","importSettings":{},"dependencies":[],"fileDependencies":[]}}},"2b":{"2b228aF-978555I-fb9096L-0ac094E":{"path":".buildin/effect/ForwardLit/material.hlsl","tempPath":"","mtime":1663412595918.9749,"meta":{"uuid":"2b228aF-978555I-fb9096L-0ac094E","importSettings":{},"dependencies":[],"fileDependencies":[]}}},"cf":{"cf1751F-9b52e3I-cbd577L-a95db3E":{"path":".buildin/effect/ForwardLit/math.hlsl","tempPath":"","mtime":1663412595984.7988,"meta":{"uuid":"cf1751F-9b52e3I-cbd577L-a95db3E","importSettings":{},"dependencies":[],"fileDependencies":[]}},"cff9dfR-04b842E-5fa5a7S-e58cabR":{"path":".buildin/Editor/loadingScene/script/retryBtn.ts","tempPath":"","mtime":1663412595630.745,"meta":{"uuid":"cff9dfR-04b842E-5fa5a7S-e58cabR","importSettings":{},"dependencies":[],"fileDependencies":[]}}},"9f":{"9ffbe3R-26dd39E-2eaf8dS-6bf180R":{"path":".buildin/effect/GaussianBlur.effect","tempPath":"","mtime":1663412596213.1885,"meta":{"uuid":"9ffbe3R-26dd39E-2eaf8dS-6bf180R","importSettings":{},"dependencies":[],"fileDependencies":[]}},"9f8acfF-806f6aI-3c33f0L-6378f7E":{"path":".buildin/effect/Text2D.pixel.hlsl","tempPath":"","mtime":1663412597674.2444,"meta":{"uuid":"9f8acfF-806f6aI-3c33f0L-6378f7E","importSettings":{},"dependencies":[],"fileDependencies":[]}},"9f04e7R-8dc3cfE-4d3a3eS-a94940R":{"path":".buildin/skybox/default_skybox_texturecube.texturecube","tempPath":"","mtime":1663412598188.8318,"meta":{"uuid":"9f04e7R-8dc3cfE-4d3a3eS-a94940R","importSettings":{},"dependencies":[],"fileDependencies":[]}},"9f6d7eF-15469eI-d02490L-24989dE":{"path":"Sprites/Button/create_room.png","tempPath":"","mtime":1649518374699.1792,"meta":{"uuid":"9f6d7eF-15469eI-d02490L-24989dE","importSettings":{},"dependencies":[],"fileDependencies":[]}}},"af":{"afa073F-380b77I-fe6a26L-d9d370E":{"path":".buildin/effect/GaussianBlurResolve.pixel.hlsl","tempPath":"","mtime":1663412596291.9155,"meta":{"uuid":"afa073F-380b77I-fe6a26L-d9d370E","importSettings":{},"dependencies":[],"fileDependencies":[]}}},"e0":{"e0c08fF-ccaedaI-903a73L-e136bdE":{"path":".buildin/effect/GaussianBlurVertical.pixel.hlsl","tempPath":"","mtime":1663412596327.81,"meta":{"uuid":"e0c08fF-ccaedaI-903a73L-e136bdE","importSettings":{},"dependencies":[],"fileDependencies":[]}},"e062c7F-36af46I-22a283L-5b2474E":{"path":"Sprites/Button/ready.png","tempPath":"","mtime":1648962642662.651,"meta":{"uuid":"e062c7F-36af46I-22a283L-5b2474E","importSettings":{},"dependencies":[],"fileDependencies":[]}},"e06c06F-a7ecb5I-bed88dL-e90ef3E":{"path":"Sprites/Poker/17.png","tempPath":"","mtime":1664246439669.6418,"meta":{"uuid":"e06c06F-a7ecb5I-bed88dL-e90ef3E","importSettings":{},"dependencies":[],"fileDependencies":[]}}},"df":{"df6f5aR-6fbfeaE-0bfd4dS-2c1c6cR":{"path":".buildin/effect/GrayScale2D.effect","tempPath":"","mtime":1663412596362.7168,"meta":{"uuid":"df6f5aR-6fbfeaE-0bfd4dS-2c1c6cR","importSettings":{},"dependencies":[],"fileDependencies":[]}},"df0288F-a5752eI-7a38aeL-2402f7E":{"path":".buildin/effect/ToneMapping.pixel.hlsl","tempPath":"","mtime":1663412597708.1174,"meta":{"uuid":"df0288F-a5752eI-7a38aeL-2402f7E","importSettings":{},"dependencies":[],"fileDependencies":[]}},"df8725R-f3915cE-6710eeS-e9654eR":{"path":".buildin/mesh/ArchRing.mesh","tempPath":"","mtime":1663412597948.474,"meta":{"uuid":"df8725R-f3915cE-6710eeS-e9654eR","importSettings":{},"dependencies":[],"fileDependencies":[]}}},"1f":{"1f7f64F-e30e87I-1e74f9L-b6fcdaE":{"path":".buildin/effect/GrayScale2D.pixel.hlsl","tempPath":"","mtime":1663412596393.6333,"meta":{"uuid":"1f7f64F-e30e87I-1e74f9L-b6fcdaE","importSettings":{},"dependencies":[],"fileDependencies":[]}},"1fa9c8F-41f364I-056c06L-7f7936E":{"path":"Sprites/Poker/32.png","tempPath":"","mtime":1664246439652.6853,"meta":{"uuid":"1fa9c8F-41f364I-056c06L-7f7936E","importSettings":{},"dependencies":[],"fileDependencies":[]}}},"e2":{"e2931cR-e5d63dE-13ccc4S-7a797dR":{"path":".buildin/effect/HDR.effect","tempPath":"","mtime":1663412596427.5427,"meta":{"uuid":"e2931cR-e5d63dE-13ccc4S-7a797dR","importSettings":{},"dependencies":[],"fileDependencies":[]}}},"db":{"dba1ebF-37cc9eI-e4e620L-612e53E":{"path":".buildin/effect/Image2D.vertex.hlsl","tempPath":"","mtime":1663412596550.215,"meta":{"uuid":"dba1ebF-37cc9eI-e4e620L-612e53E","importSettings":{},"dependencies":[],"fileDependencies":[]}},"db2a99F-633888I-5f3361L-ac17a1E":{"path":".buildin/effect/ShadowCasterFallBack.pixel.hlsl","tempPath":"","mtime":1663412596685.8513,"meta":{"uuid":"db2a99F-633888I-5f3361L-ac17a1E","importSettings":{},"dependencies":[],"fileDependencies":[]}},"dbfdfdR-5a8578E-a92a80S-252951R":{"path":".buildin/Editor/loadingScene/common/Utils.ts","tempPath":"","mtime":1663412595529.0176,"meta":{"uuid":"dbfdfdR-5a8578E-a92a80S-252951R","importSettings":{},"dependencies":[],"fileDependencies":[]}}},"ec":{"ec27ccR-ba688fE-364978S-923276R":{"path":".buildin/effect/Mask2D.effect","tempPath":"","mtime":1663412596580.134,"meta":{"uuid":"ec27ccR-ba688fE-364978S-923276R","importSettings":{},"dependencies":[],"fileDependencies":[]}},"ec7485R-8b91adE-8a13e9S-abdfcfR":{"path":".buildin/Editor/loadingScene/progressbar/UIProgressBar.prefab","tempPath":"","mtime":1663412595609.8022,"meta":{"uuid":"ec7485R-8b91adE-8a13e9S-abdfcfR","importSettings":{},"dependencies":[],"fileDependencies":[]}}},"7f":{"7feab8F-e35282I-f8ca36L-dafe93E":{"path":".buildin/effect/Screen.pixel.hlsl","tempPath":"","mtime":1663412596606.0652,"meta":{"uuid":"7feab8F-e35282I-f8ca36L-dafe93E","importSettings":{},"dependencies":[],"fileDependencies":[]}}},"f0":{"f0c3d7F-8db8e3I-3691daL-5f176dE":{"path":".buildin/effect/Screen.vertex.hlsl","tempPath":"","mtime":1663412596630.9983,"meta":{"uuid":"f0c3d7F-8db8e3I-3691daL-5f176dE","importSettings":{},"dependencies":[],"fileDependencies":[]}},"f0efa4F-19cec0I-9e915eL-b19930E":{"path":".buildin/Editor/defaultAssetsFiles/avatar.bin","tempPath":"","mtime":1663412595504.084,"meta":{"uuid":"f0efa4F-19cec0I-9e915eL-b19930E","importSettings":{},"dependencies":[],"fileDependencies":[]}}},"a0":{"a015d5R-d0771eE-be912dS-f16081R":{"path":".buildin/effect/ShadowCasterFallBack.effect","tempPath":"","mtime":1663412596655.932,"meta":{"uuid":"a015d5R-d0771eE-be912dS-f16081R","importSettings":{},"dependencies":[],"fileDependencies":[]}}},"ab":{"abe8a2F-51d048I-c239c8L-589761E":{"path":".buildin/effect/ShadowCasterFallBack.vertex.hlsl","tempPath":"","mtime":1663412596976.0745,"meta":{"uuid":"abe8a2F-51d048I-c239c8L-589761E","importSettings":{},"dependencies":[],"fileDependencies":[]}}},"1c":{"1c758aR-85db0eE-d0aa94S-67b2d4R":{"path":".buildin/effect/ShowCubeMap.effect","tempPath":"","mtime":1663412597056.8606,"meta":{"uuid":"1c758aR-85db0eE-d0aa94S-67b2d4R","importSettings":{},"dependencies":[],"fileDependencies":[]}},"1c75a2F-9ffc56I-5dc027L-ecd17aE":{"path":"Sprites/Poker/16.png","tempPath":"","mtime":1664246439645.7039,"meta":{"uuid":"1c75a2F-9ffc56I-5dc027L-ecd17aE","importSettings":{},"dependencies":[],"fileDependencies":[]}}},"ce":{"ce1358F-655db1I-b6fb00L-3617c1E":{"path":".buildin/effect/ShowCubeMap.vertex.hlsl","tempPath":"","mtime":1663412597115.7024,"meta":{"uuid":"ce1358F-655db1I-b6fb00L-3617c1E","importSettings":{},"dependencies":[],"fileDependencies":[]}}},"d0":{"d08196R-9a6914E-21f968S-ef5e28R":{"path":".buildin/effect/Simple3D.effect","tempPath":"","mtime":1663412597142.6294,"meta":{"uuid":"d08196R-9a6914E-21f968S-ef5e28R","importSettings":{},"dependencies":[],"fileDependencies":[]}}},"3e":{"3ec515F-000d96I-ffe3fdL-d995e4E":{"path":".buildin/effect/Simple3D.vertex.hlsl","tempPath":"","mtime":1663412597197.4827,"meta":{"uuid":"3ec515F-000d96I-ffe3fdL-d995e4E","importSettings":{},"dependencies":[],"fileDependencies":[]}},"3e818cF-368ca7I-af6357L-5d6c09E":{"path":"Sprites/Poker/7.png","tempPath":"","mtime":1664246439709.5635,"meta":{"uuid":"3e818cF-368ca7I-af6357L-5d6c09E","importSettings":{},"dependencies":[],"fileDependencies":[]}}},"2c":{"2c795aR-a40aecE-8c06a8S-993847R":{"path":".buildin/effect/Skybox.effect","tempPath":"","mtime":1663412597224.4116,"meta":{"uuid":"2c795aR-a40aecE-8c06a8S-993847R","importSettings":{},"dependencies":[],"fileDependencies":[]}}},"bb":{"bb3cfdF-137903I-3b0b73L-f44453E":{"path":".buildin/effect/Skybox.vertex.hlsl","tempPath":"","mtime":1663412597274.2773,"meta":{"uuid":"bb3cfdF-137903I-3b0b73L-f44453E","importSettings":{},"dependencies":[],"fileDependencies":[]}},"bb39f8F-532329I-fb2328L-9cfc62E":{"path":"Sprites/Poker/22.png","tempPath":"","mtime":1664246439692.5786,"meta":{"uuid":"bb39f8F-532329I-fb2328L-9cfc62E","importSettings":{},"dependencies":[],"fileDependencies":[]}}},"f6":{"f67be2R-569aabE-e0bc32S-23089dR":{"path":".buildin/effect/Terrain3.effect","tempPath":"","mtime":1663412597447.8135,"meta":{"uuid":"f67be2R-569aabE-e0bc32S-23089dR","importSettings":{},"dependencies":[],"fileDependencies":[]}}},"3c":{"3cfbbfF-dea749I-a2bbdcL-5123baE":{"path":".buildin/effect/Terrain4.pixel.hlsl","tempPath":"","mtime":1663412597575.4717,"meta":{"uuid":"3cfbbfF-dea749I-a2bbdcL-5123baE","importSettings":{},"dependencies":[],"fileDependencies":[]}},"3cff32F-68f37eI-d441e3L-f3b41cE":{"path":"Sprites/Poker/2.png","tempPath":"","mtime":1664246439684.6,"meta":{"uuid":"3cff32F-68f37eI-d441e3L-f3b41cE","importSettings":{},"dependencies":[],"fileDependencies":[]}}},"0b":{"0b238bR-378266E-4fd61aS-7c48faR":{"path":".buildin/effect/UI3D.effect","tempPath":"","mtime":1663412597740.0334,"meta":{"uuid":"0b238bR-378266E-4fd61aS-7c48faR","importSettings":{},"dependencies":[],"fileDependencies":[]}},"0b2cdeF-297fa8I-50b85cL-f5d747E":{"path":".buildin/skybox/default_skybox_side.png","tempPath":"","mtime":1663412598181.8503,"meta":{"uuid":"0b2cdeF-297fa8I-50b85cL-f5d747E","importSettings":{},"dependencies":[],"fileDependencies":[]}},"0bf100F-d5a417I-62a8e3L-80ec54E":{"path":"Sprites/Poker/4.png","tempPath":"","mtime":1664246439638.723,"meta":{"uuid":"0bf100F-d5a417I-62a8e3L-80ec54E","importSettings":{},"dependencies":[],"fileDependencies":[]}}},"8b":{"8b5c31R-2cd3adE-9a8c20S-c5d650R":{"path":".buildin/ui/buildin_default_button.spriteframe","tempPath":"","mtime":1663412598256.651,"meta":{"uuid":"8b5c31R-2cd3adE-9a8c20S-c5d650R","importSettings":{},"dependencies":[],"fileDependencies":[]}}},"04":{"04db7cR-70c833E-83829fS-605c11R":{"path":".buildin/ui/buildin_default_image.spriteframe","tempPath":"","mtime":1663412598271.611,"meta":{"uuid":"04db7cR-70c833E-83829fS-605c11R","importSettings":{},"dependencies":[],"fileDependencies":[]}}},"7b":{"7b625eF-9cdc6cI-7080e3L-83bd28E":{"path":".buildin/Editor/billboardImage/audio-listener.png","tempPath":"","mtime":1663412595322.5698,"meta":{"uuid":"7b625eF-9cdc6cI-7080e3L-83bd28E","importSettings":{},"dependencies":[],"fileDependencies":[]}},"7bf949F-aedaabI-74042dL-761941E":{"path":"Sprites/Poker/31.png","tempPath":"","mtime":1664246439721.5022,"meta":{"uuid":"7bf949F-aedaabI-74042dL-761941E","importSettings":{},"dependencies":[],"fileDependencies":[]}}},"da":{"daecb8F-f763b3I-0abb78L-6293d9E":{"path":".buildin/Editor/billboardImage/directional-light.png","tempPath":"","mtime":1663412595342.5193,"meta":{"uuid":"daecb8F-f763b3I-0abb78L-6293d9E","importSettings":{},"dependencies":[],"fileDependencies":[]}}},"a1":{"a1bbc4F-ac1d79I-052262L-8c6e46E":{"path":".buildin/Editor/billboardImage/point-light.png","tempPath":"","mtime":1663412595356.4792,"meta":{"uuid":"a1bbc4F-ac1d79I-052262L-8c6e46E","importSettings":{},"dependencies":[],"fileDependencies":[]}}},"5f":{"5f86e2F-8707f4I-520037L-fae414E":{"path":".buildin/Editor/billboardImage/spot-light.png","tempPath":"","mtime":1663412595365.4897,"meta":{"uuid":"5f86e2F-8707f4I-520037L-fae414E","importSettings":{},"dependencies":[],"fileDependencies":[]}}},"ae":{"ae0127R-ff0501E-6d2cb4S-1dba39R":{"path":".buildin/Editor/defaultAssets/animationclip.animationclip","tempPath":"","mtime":1663412595378.4214,"meta":{"uuid":"ae0127R-ff0501E-6d2cb4S-1dba39R","importSettings":{},"dependencies":[],"fileDependencies":[]}},"ae2ae0R-24a131E-5b05cbS-131762R":{"path":".buildin/Editor/defaultAssets/physicmaterial.physicmaterial","tempPath":"","mtime":1663412595432.279,"meta":{"uuid":"ae2ae0R-24a131E-5b05cbS-131762R","importSettings":{},"dependencies":[],"fileDependencies":[]}}},"1e":{"1e5544R-612e12E-6750a4S-97782dR":{"path":".buildin/Editor/defaultAssets/avatarmask.avatarmask","tempPath":"","mtime":1663412595398.368,"meta":{"uuid":"1e5544R-612e12E-6750a4S-97782dR","importSettings":{},"dependencies":[],"fileDependencies":[]}}},"d3":{"d3033bR-86c5feE-26da50S-28ecb5R":{"path":".buildin/Editor/defaultAssets/bitmapfont.bitmapfont","tempPath":"","mtime":1663412595404.3513,"meta":{"uuid":"d3033bR-86c5feE-26da50S-28ecb5R","importSettings":{},"dependencies":[],"fileDependencies":[]}},"d3b66aF-e8c915I-e6ca73L-dfc469E":{"path":".buildin/mesh/Cylinder.mesh.bin","tempPath":"","mtime":1663412598022.2769,"meta":{"uuid":"d3b66aF-e8c915I-e6ca73L-dfc469E","importSettings":{},"dependencies":[],"fileDependencies":[]}},"d3d1a3F-fcd657I-a3e7a5L-8e6313E":{"path":"Sprites/Poker/11.png","tempPath":"","mtime":1664246439715.5188,"meta":{"uuid":"d3d1a3F-fcd657I-a3e7a5L-8e6313E","importSettings":{},"dependencies":[],"fileDependencies":[]}},"d35227F-951591I-b951cdL-d93d33E":{"path":"Sprites/Poker/6.png","tempPath":"","mtime":1664246439685.5972,"meta":{"uuid":"d35227F-951591I-b951cdL-d93d33E","importSettings":{},"dependencies":[],"fileDependencies":[]}}},"c6":{"c61ad8R-551dabE-b14115S-9f826cR":{"path":".buildin/Editor/defaultAssets/material.mat","tempPath":"","mtime":1663412595413.3274,"meta":{"uuid":"c61ad8R-551dabE-b14115S-9f826cR","importSettings":{},"dependencies":[],"fileDependencies":[]}}},"01":{"01d8eaR-b9a07cE-2b76f1S-5eff61R":{"path":".buildin/Editor/defaultAssets/prefab2d.prefab","tempPath":"","mtime":1663412595441.2532,"meta":{"uuid":"01d8eaR-b9a07cE-2b76f1S-5eff61R","importSettings":{},"dependencies":[],"fileDependencies":[]}},"016a55F-d9ea6bI-17dac5L-174725E":{"path":".buildin/Editor/loadingScene/icon.png","tempPath":"","mtime":1663412595535.003,"meta":{"uuid":"016a55F-d9ea6bI-17dac5L-174725E","importSettings":{},"dependencies":[],"fileDependencies":[]}}},"4a":{"4a89a9R-ea6670E-a9d7d0S-b38e9bR":{"path":".buildin/Editor/defaultAssets/prefab3d.prefab","tempPath":"","mtime":1663412595451.2256,"meta":{"uuid":"4a89a9R-ea6670E-a9d7d0S-b38e9bR","importSettings":{},"dependencies":[],"fileDependencies":[]}},"4af073R-ad6d32E-af94d6S-72830eR":{"path":"Scripts/utils.ts","tempPath":"","mtime":1664786202564.155,"meta":{"uuid":"4af073R-ad6d32E-af94d6S-72830eR","importSettings":{},"dependencies":[],"fileDependencies":[]}}},"e7":{"e74694R-6f4f7dE-f12ae0S-007123R":{"path":".buildin/Editor/defaultAssets/scriptableasset.ts","tempPath":"","mtime":1663412595472.1694,"meta":{"uuid":"e74694R-6f4f7dE-f12ae0S-007123R","importSettings":{},"dependencies":[],"fileDependencies":[]}},"e71495F-8aa3a9I-7497a0L-cc911aE":{"path":"Sprites/Background/bg1.jpg","tempPath":"","mtime":1648298652744.2458,"meta":{"uuid":"e71495F-8aa3a9I-7497a0L-cc911aE","importSettings":{},"dependencies":[],"fileDependencies":[]}}},"bd":{"bd0979R-a7b1bcE-71857cS-e89112R":{"path":".buildin/Editor/defaultAssets/texturecube.texturecube","tempPath":"","mtime":1663412595485.1477,"meta":{"uuid":"bd0979R-a7b1bcE-71857cS-e89112R","importSettings":{},"dependencies":[],"fileDependencies":[]}},"bd4c2eF-9d3a30I-7712b0L-4baf6dE":{"path":"Sprites/Poker/28.png","tempPath":"","mtime":1664246439650.6907,"meta":{"uuid":"bd4c2eF-9d3a30I-7712b0L-4baf6dE","importSettings":{},"dependencies":[],"fileDependencies":[]}}},"6c":{"6c7e51F-ba6d82I-0335a7L-c5b6caE":{"path":".buildin/Editor/defaultAssetsFiles/mesh.bin","tempPath":"","mtime":1663412595517.0505,"meta":{"uuid":"6c7e51F-ba6d82I-0335a7L-c5b6caE","importSettings":{},"dependencies":[],"fileDependencies":[]}},"6cf0f6R-80cf57E-884646S-fa67d1R":{"path":"Sprites/poker.tplist","tempPath":"","mtime":1651990810062.5542,"meta":{"uuid":"6cf0f6R-80cf57E-884646S-fa67d1R","importSettings":{},"dependencies":[],"fileDependencies":[]}}},"3b":{"3b5586R-089f24E-534f8cS-4d73f6R":{"path":".buildin/Editor/loadingScene/loading.scene","tempPath":"","mtime":1663412595543.9788,"meta":{"uuid":"3b5586R-089f24E-534f8cS-4d73f6R","importSettings":{},"dependencies":[],"fileDependencies":[]}}},"00":{"002e72F-be6b31I-48198bL-d87728E":{"path":".buildin/Editor/loadingScene/progressbar/resource/Progress_Background.png","tempPath":"","mtime":1663412595558.9387,"meta":{"uuid":"002e72F-be6b31I-48198bL-d87728E","importSettings":{},"dependencies":[],"fileDependencies":[]}}},"a3":{"a3849cR-582efeE-be8a78S-d06846R":{"path":".buildin/Editor/loadingScene/progressbar/scripts/UIProgressBar.ts","tempPath":"","mtime":1663412595588.8574,"meta":{"uuid":"a3849cR-582efeE-be8a78S-d06846R","importSettings":{},"dependencies":[],"fileDependencies":[]}}},"07":{"070b6bR-cefe4fE-2a0cddS-01907dR":{"path":".buildin/Editor/tutorial/default-tutorial-hooks.ts","tempPath":"","mtime":1663412595649.6943,"meta":{"uuid":"070b6bR-cefe4fE-2a0cddS-01907dR","importSettings":{},"dependencies":[],"fileDependencies":[]}},"07cd21F-ebaf13I-562d0aL-09c585E":{"path":"Sprites/Button/bg.png","tempPath":"","mtime":1643890547000,"meta":{"uuid":"07cd21F-ebaf13I-562d0aL-09c585E","importSettings":{},"dependencies":[],"fileDependencies":[]}}},"b5":{"b591cfF-4b9518I-0a532dL-6fbcd9E":{"path":".buildin/mesh/ArchRing.mesh.bin","tempPath":"","mtime":1663412597953.4624,"meta":{"uuid":"b591cfF-4b9518I-0a532dL-6fbcd9E","importSettings":{},"dependencies":[],"fileDependencies":[]}}},"ee":{"ee651cF-5e0700I-34a80fL-63f5a0E":{"path":".buildin/mesh/Cube.mesh.bin","tempPath":"","mtime":1663412598002.3306,"meta":{"uuid":"ee651cF-5e0700I-34a80fL-63f5a0E","importSettings":{},"dependencies":[],"fileDependencies":[]}}},"ed":{"ed221cR-cd1bd5E-07e51aS-de50bcR":{"path":".buildin/mesh/Cylinder.mesh","tempPath":"","mtime":1663412598016.293,"meta":{"uuid":"ed221cR-cd1bd5E-07e51aS-de50bcR","importSettings":{},"dependencies":[],"fileDependencies":[]}}},"d4":{"d4284fR-f334a3E-ed3a05S-5b61acR":{"path":".buildin/mesh/Ring.mesh","tempPath":"","mtime":1663412598086.1062,"meta":{"uuid":"d4284fR-f334a3E-ed3a05S-5b61acR","importSettings":{},"dependencies":[],"fileDependencies":[]}}},"e6":{"e6d2fcF-78ac67I-d99cb2L-f62fc0E":{"path":".buildin/mesh/Ring.mesh.bin","tempPath":"","mtime":1663412598092.09,"meta":{"uuid":"e6d2fcF-78ac67I-d99cb2L-f62fc0E","importSettings":{},"dependencies":[],"fileDependencies":[]}}},"05":{"05d173R-41cc52E-86e45bS-52ae33R":{"path":"intro.md","tempPath":"","mtime":1663644602330.2173,"meta":{"uuid":"05d173R-41cc52E-86e45bS-52ae33R","importSettings":{},"dependencies":[],"fileDependencies":[]}}},"bc":{"bc2b3bF-7ed19bI-929628L-bb491aE":{"path":"package.json","tempPath":"","mtime":1663412576337.602,"meta":{"uuid":"bc2b3bF-7ed19bI-929628L-bb491aE","importSettings":{},"dependencies":[],"fileDependencies":[]}},"bc2fabR-2ae82bE-8a2194S-a23890R":{"path":"Scripts/TeamPlayResult.ts","tempPath":"","mtime":1664765913355.2144,"meta":{"uuid":"bc2fabR-2ae82bE-8a2194S-a23890R","importSettings":{},"dependencies":[],"fileDependencies":[]}}},"d2":{"d2ed41F-3655b2I-3aae25L-cca5fbE":{"path":"Sprites/be_ready.png","tempPath":"","mtime":1651993007122.8167,"meta":{"uuid":"d2ed41F-3655b2I-3aae25L-cca5fbE","importSettings":{},"dependencies":[],"fileDependencies":[]}}},"b1":{"b1807fR-2a768cE-25d3fbS-f77babR":{"path":"Prefabs/MyHandCard.prefab","tempPath":"","mtime":1664621881787.1628,"meta":{"uuid":"b1807fR-2a768cE-25d3fbS-f77babR","importSettings":{},"dependencies":[],"fileDependencies":[]}},"b115afR-29f268E-b05f56S-5bdc71R":{"path":"Scripts/MyScore.ts","tempPath":"","mtime":1664705542562.0837,"meta":{"uuid":"b115afR-29f268E-b05f56S-5bdc71R","importSettings":{},"dependencies":[],"fileDependencies":[]}},"b1cec5F-070c98I-e5d65eL-62cbbdE":{"path":"Sprites/Button/pass.png","tempPath":"","mtime":1665290592492.447,"meta":{"uuid":"b1cec5F-070c98I-e5d65eL-62cbbdE","importSettings":{},"dependencies":[],"fileDependencies":[]}}},"f4":{"f4a3c8F-c5a7dbI-59d102L-635323E":{"path":"Sprites/clock.png","tempPath":"","mtime":1648962642671.6277,"meta":{"uuid":"f4a3c8F-c5a7dbI-59d102L-635323E","importSettings":{},"dependencies":[],"fileDependencies":[]}}},"2e":{"2ed74dF-085c05I-92f543L-f3f2daE":{"path":"Sprites/frame.png","tempPath":"","mtime":1648962642720.4988,"meta":{"uuid":"2ed74dF-085c05I-92f543L-f3f2daE","importSettings":{},"dependencies":[],"fileDependencies":[]}}},"cd":{"cdfea4R-c0c89aE-af208bS-901661R":{"path":"Scripts/GameServer.ts","tempPath":"","mtime":1664102888309.1028,"meta":{"uuid":"cdfea4R-c0c89aE-af208bS-901661R","importSettings":{},"dependencies":[],"fileDependencies":[]}}},"dd":{"dd4ae3F-02a793I-33fba3L-adbab9E":{"path":"Sprites/host.png","tempPath":"","mtime":1648962642686.5884,"meta":{"uuid":"dd4ae3F-02a793I-33fba3L-adbab9E","importSettings":{},"dependencies":[],"fileDependencies":[]}}},"e3":{"e375f1F-5cb519I-e067beL-e44686E":{"path":"Sprites/Background/bg0.png","tempPath":"","mtime":1648962642737.4514,"meta":{"uuid":"e375f1F-5cb519I-e067beL-e44686E","importSettings":{},"dependencies":[],"fileDependencies":[]}}},"e8":{"e8ea5aF-cd55f9I-7dc13eL-2cf3d1E":{"path":"Sprites/Background/bg2.png","tempPath":"","mtime":1648962642746.4272,"meta":{"uuid":"e8ea5aF-cd55f9I-7dc13eL-2cf3d1E","importSettings":{},"dependencies":[],"fileDependencies":[]}},"e83c2aF-a4c531I-3632d2L-231c7dE":{"path":"Sprites/Poker/18.png","tempPath":"","mtime":1664246439690.5852,"meta":{"uuid":"e83c2aF-a4c531I-3632d2L-231c7dE","importSettings":{},"dependencies":[],"fileDependencies":[]}}},"b8":{"b88bbeF-9a98ecI-8a4c63L-b25047E":{"path":"Sprites/Button/exit.png","tempPath":"","mtime":1647848072382.294,"meta":{"uuid":"b88bbeF-9a98ecI-8a4c63L-b25047E","importSettings":{},"dependencies":[],"fileDependencies":[]}},"b837a2R-14ea59E-dcf6d6S-f416f0R":{"path":"Scripts/CreateRoom.ts","tempPath":"","mtime":1664707735913.4976,"meta":{"uuid":"b837a2R-14ea59E-dcf6d6S-f416f0R","importSettings":{},"dependencies":[],"fileDependencies":[]}}},"c3":{"c3ad49F-d6920cI-b7263fL-ea1017E":{"path":"Sprites/Poker/41.png","tempPath":"","mtime":1664246439679.655,"meta":{"uuid":"c3ad49F-d6920cI-b7263fL-ea1017E","importSettings":{},"dependencies":[],"fileDependencies":[]}}},"b4":{"b44227F-e14fe2I-ce0b07L-44fcd8E":{"path":"Sprites/Button/start.png","tempPath":"","mtime":1648962642650.683,"meta":{"uuid":"b44227F-e14fe2I-ce0b07L-44fcd8E","importSettings":{},"dependencies":[],"fileDependencies":[]}}},"d6":{"d629b0R-5f2c01E-512d2fS-2532f0R":{"path":"Scenes/Room.scene","tempPath":"","mtime":1665315262261.3914,"meta":{"uuid":"d629b0R-5f2c01E-512d2fS-2532f0R","importSettings":{},"dependencies":[],"fileDependencies":[]}}},"d5":{"d5edb2R-248ce6E-ba1f22S-3c93ffR":{"path":"Scripts/ExitRoom.ts","tempPath":"","mtime":1664707776846.8816,"meta":{"uuid":"d5edb2R-248ce6E-ba1f22S-3c93ffR","importSettings":{},"dependencies":[],"fileDependencies":[]}}},"8f":{"8f40a9F-15979cI-34a3e5L-0b6742E":{"path":"Sprites/Poker/3.png","tempPath":"","mtime":1664246439707.5398,"meta":{"uuid":"8f40a9F-15979cI-34a3e5L-0b6742E","importSettings":{},"dependencies":[],"fileDependencies":[]}}},"f2":{"f2d221F-1bd236I-0dec4bL-ce078bE":{"path":"Sprites/Poker/0.png","tempPath":"","mtime":1664246439636.728,"meta":{"uuid":"f2d221F-1bd236I-0dec4bL-ce078bE","importSettings":{},"dependencies":[],"fileDependencies":[]}}},"4c":{"4c581cF-dbe404I-2083c3L-6c4501E":{"path":"Sprites/Poker/20.png","tempPath":"","mtime":1664246439647.7146,"meta":{"uuid":"4c581cF-dbe404I-2083c3L-6c4501E","importSettings":{},"dependencies":[],"fileDependencies":[]}}},"e5":{"e50a65F-e426aaI-ac9b81L-4cb838E":{"path":"Sprites/Poker/21.png","tempPath":"","mtime":1664246439671.6357,"meta":{"uuid":"e50a65F-e426aaI-ac9b81L-4cb838E","importSettings":{},"dependencies":[],"fileDependencies":[]}}},"06":{"06f35aF-69643fI-5247feL-a0f09dE":{"path":"Sprites/Poker/23.png","tempPath":"","mtime":1664246439719.541,"meta":{"uuid":"06f35aF-69643fI-5247feL-a0f09dE","importSettings":{},"dependencies":[],"fileDependencies":[]}},"06717aF-217c27I-376ce6L-0ab738E":{"path":"Sprites/Poker/39.png","tempPath":"","mtime":1664246439725.4912,"meta":{"uuid":"06717aF-217c27I-376ce6L-0ab738E","importSettings":{},"dependencies":[],"fileDependencies":[]}},"0612aeF-84a2f3I-2dd555L-06e48dE":{"path":"Sprites/Poker/45.png","tempPath":"","mtime":1664246439681.6387,"meta":{"uuid":"0612aeF-84a2f3I-2dd555L-06e48dE","importSettings":{},"dependencies":[],"fileDependencies":[]}}},"a6":{"a6e86bF-ddf5efI-a2a221L-f27583E":{"path":"Sprites/Poker/24.png","tempPath":"","mtime":1664246439649.693,"meta":{"uuid":"a6e86bF-ddf5efI-a2a221L-f27583E","importSettings":{},"dependencies":[],"fileDependencies":[]}}},"c5":{"c54b6fF-6c922aI-b068b6L-46072bE":{"path":"Sprites/Poker/25.png","tempPath":"","mtime":1664246439673.6306,"meta":{"uuid":"c54b6fF-6c922aI-b068b6L-46072bE","importSettings":{},"dependencies":[],"fileDependencies":[]}}},"c8":{"c816a6F-824abcI-700e74L-cb7ce8E":{"path":"Sprites/Poker/35.png","tempPath":"","mtime":1664246439724.4934,"meta":{"uuid":"c816a6F-824abcI-700e74L-cb7ce8E","importSettings":{},"dependencies":[],"fileDependencies":[]}}},"6d":{"6df67fF-6eff7eI-63b55eL-cb8d3dE":{"path":"Sprites/Poker/37.png","tempPath":"","mtime":1664246439678.6904,"meta":{"uuid":"6df67fF-6eff7eI-63b55eL-cb8d3dE","importSettings":{},"dependencies":[],"fileDependencies":[]}}},"0c":{"0cf20dF-76a72dI-9ac4bbL-d34f82E":{"path":"Sprites/Poker/38.png","tempPath":"","mtime":1664246439698.5623,"meta":{"uuid":"0cf20dF-76a72dI-9ac4bbL-d34f82E","importSettings":{},"dependencies":[],"fileDependencies":[]}}},"8c":{"8ccf97F-e3b40fI-92c9a5L-fac28bE":{"path":"Sprites/Poker/43.png","tempPath":"","mtime":1664246439727.525,"meta":{"uuid":"8ccf97F-e3b40fI-92c9a5L-fac28bE","importSettings":{},"dependencies":[],"fileDependencies":[]}}},"c1":{"c108adF-0373e4I-7fcc3bL-6fc3f8E":{"path":"Sprites/Poker/44.png","tempPath":"","mtime":1664246439659.6675,"meta":{"uuid":"c108adF-0373e4I-7fcc3bL-6fc3f8E","importSettings":{},"dependencies":[],"fileDependencies":[]}}},"fb":{"fb535cF-62cd4aI-72fac3L-a3bf49E":{"path":"Sprites/Poker/49.png","tempPath":"","mtime":1664246439682.6514,"meta":{"uuid":"fb535cF-62cd4aI-72fac3L-a3bf49E","importSettings":{},"dependencies":[],"fileDependencies":[]}}},"c0":{"c0377bF-4408ccI-c981eaL-46c36fE":{"path":"Sprites/Poker/51.png","tempPath":"","mtime":1664246439730.513,"meta":{"uuid":"c0377bF-4408ccI-c981eaL-46c36fE","importSettings":{},"dependencies":[],"fileDependencies":[]}}},"2d":{"2d3bc1F-78ef24I-b0784bL-3bdbe3E":{"path":"Sprites/Poker/9.png","tempPath":"","mtime":1664246439666.6477,"meta":{"uuid":"2d3bc1F-78ef24I-b0784bL-3bdbe3E","importSettings":{},"dependencies":[],"fileDependencies":[]}}},"f1":{"f192baR-1cf2fdE-c18c6eS-97c950R":{"path":"Prefabs/RemainingCardCount.prefab","tempPath":"","mtime":1664622410486.785,"meta":{"uuid":"f192baR-1cf2fdE-c18c6eS-97c950R","importSettings":{},"dependencies":[],"fileDependencies":[]}}},"dc":{"dcd06fR-113b75E-511961S-fef74fR":{"path":"Prefabs/BankerCard.prefab","tempPath":"","mtime":1664627079389.955,"meta":{"uuid":"dcd06fR-113b75E-511961S-fef74fR","importSettings":{},"dependencies":[],"fileDependencies":[]}}},"cc":{"cc36f1R-dafc8bE-b19d5dS-89a731R":{"path":"Scripts/PlayerBattle.ts","tempPath":"","mtime":1664777001791.8423,"meta":{"uuid":"cc36f1R-dafc8bE-b19d5dS-89a731R","importSettings":{},"dependencies":[],"fileDependencies":[]}}},"b3":{"b3cf02R-97d6b0E-705a48S-904e7eR":{"path":"Scripts/MyInfo.ts","tempPath":"","mtime":1664726133268.472,"meta":{"uuid":"b3cf02R-97d6b0E-705a48S-904e7eR","importSettings":{},"dependencies":[],"fileDependencies":[]}}},"ca":{"ca128eR-2f1ed8E-a1e07eS-8d7f7cR":{"path":"Scripts/PlayerInfo.ts","tempPath":"","mtime":1664726444629.5747,"meta":{"uuid":"ca128eR-2f1ed8E-a1e07eS-8d7f7cR","importSettings":{},"dependencies":[],"fileDependencies":[]}}},"b9":{"b94f08R-818716E-d0d48dS-3f6ca2R":{"path":"Scripts/PlayerRemainingCardCount.ts","tempPath":"","mtime":1664706145650.1682,"meta":{"uuid":"b94f08R-818716E-d0d48dS-3f6ca2R","importSettings":{},"dependencies":[],"fileDependencies":[]}},"b9bc1dF-9e4e7eI-4484b6L-cc3484E":{"path":"Sprites/Button/play.png","tempPath":"","mtime":1665290586019.8125,"meta":{"uuid":"b9bc1dF-9e4e7eI-4484b6L-cc3484E","importSettings":{},"dependencies":[],"fileDependencies":[]}}},"6e":{"6ef825R-15b704E-0e6620S-506758R":{"path":"Scripts/Invite.ts","tempPath":"","mtime":1664707926410.3562,"meta":{"uuid":"6ef825R-15b704E-0e6620S-506758R","importSettings":{},"dependencies":[],"fileDependencies":[]}}},"03":{"036049F-9b3419I-574157L-3e6c85E":{"path":"Sprites/Button/skip.png","tempPath":"","mtime":1665290584049.4612,"meta":{"uuid":"036049F-9b3419I-574157L-3e6c85E","importSettings":{},"dependencies":[],"fileDependencies":[]}}},"4f":{"4f4268F-6ee730I-eb69abL-7e963fE":{"path":"Sprites/Button/tip.png","tempPath":"","mtime":1665291838623.5796,"meta":{"uuid":"4f4268F-6ee730I-eb69abL-7e963fE","importSettings":{},"dependencies":[],"fileDependencies":[]}}}}}