{"VERSION":"0.0.12","engineVersion":"","uuidToPath":{"13":{"13087dR-6d4ba4E-b482a5S-4bcabdR":{"path":"__temp/buildOnlyScriptProcess/typeScriptProcess/Scripts/MatchRoom.js","tempPath":"","meta":{"uuid":"13087dR-6d4ba4E-b482a5S-4bcabdR","importSettings":{"processer":{"processVersion":"v2","fromLast":["13087dR-6d4ba4E-b482a5S-4bcabdR"],"fromSrc":["13087dR-6d4ba4E-b482a5S-4bcabdR"],"relatedSrcUuid":"13087dR-6d4ba4E-b482a5S-4bcabdR","ideDisplayAssetPath":"Scripts/MatchRoom.ts","tempPath":"","loaderPath":"Scripts/MatchRoom.ts","processName":"typeScriptProcess"},"inheritGroupId":true,"groupId":"","isEntries":"false","recursiveSetEntries":true,"isPackInBuildIn":"false"},"ver":"1","size":319,"srcHash":"c608c525a9c59d773a8640184ce7a3e9","hash":"d26f84b2980ed3c6fa3cf35f04f197c4","dependencies":[],"fileDependencies":[],"service":"processService"}}},"17":{"1740d7R-c7fa0eE-f38cd8S-91f8bbR":{"path":"__temp/buildOnlyScriptProcess/typeScriptProcess/.buildin/Editor/loadingScene/script/loadMainScenes.js","tempPath":"","meta":{"uuid":"1740d7R-c7fa0eE-f38cd8S-91f8bbR","importSettings":{"processer":{"processVersion":"v2","fromLast":["1740d7R-c7fa0eE-f38cd8S-91f8bbR"],"fromSrc":["1740d7R-c7fa0eE-f38cd8S-91f8bbR"],"relatedSrcUuid":"1740d7R-c7fa0eE-f38cd8S-91f8bbR","ideDisplayAssetPath":".buildin/Editor/loadingScene/script/loadMainScenes.ts","tempPath":"","loaderPath":".buildin/Editor/loadingScene/script/loadMainScenes.ts","processName":"typeScriptProcess"},"inheritGroupId":true,"groupId":"","isEntries":"false","recursiveSetEntries":true,"isPackInBuildIn":"false"},"ver":"1","size":3412,"srcHash":"dad7e5c04cf9f15116344aeff2044cfc","hash":"59a361a41df7246dfe802a087e351817","dependencies":[],"fileDependencies":[],"service":"processService"}}},"30":{"3061fcR-4c22f3E-95eabaS-6ee851R":{"path":"__temp/buildOnlyScriptProcess/typeScriptProcess/Scripts/GlobalManager.js","tempPath":"","meta":{"uuid":"3061fcR-4c22f3E-95eabaS-6ee851R","importSettings":{"processer":{"processVersion":"v2","fromLast":["3061fcR-4c22f3E-95eabaS-6ee851R"],"fromSrc":["3061fcR-4c22f3E-95eabaS-6ee851R"],"relatedSrcUuid":"3061fcR-4c22f3E-95eabaS-6ee851R","ideDisplayAssetPath":"Scripts/GlobalManager.ts","tempPath":"","loaderPath":"Scripts/GlobalManager.ts","processName":"typeScriptProcess"},"inheritGroupId":true,"groupId":"","isEntries":"false","recursiveSetEntries":true,"isPackInBuildIn":"false"},"ver":"1","size":333,"srcHash":"0e0e7f36fa39ab3576dc90a4b64b8507","hash":"10f54602cf2eaaea7c088af164cd3c7c","dependencies":[],"fileDependencies":[],"service":"processService"}}},"57":{"57d21aR-e9016eE-ab534aS-92e1afR":{"path":"__temp/buildOnlyScriptProcess/typeScriptProcess/.buildin/Editor/defaultAssets/script.js","tempPath":"","meta":{"uuid":"57d21aR-e9016eE-ab534aS-92e1afR","importSettings":{"processer":{"processVersion":"v2","fromLast":["57d21aR-e9016eE-ab534aS-92e1afR"],"fromSrc":["57d21aR-e9016eE-ab534aS-92e1afR"],"relatedSrcUuid":"57d21aR-e9016eE-ab534aS-92e1afR","ideDisplayAssetPath":".buildin/Editor/defaultAssets/script.ts","tempPath":"","loaderPath":".buildin/Editor/defaultAssets/script.ts","processName":"typeScriptProcess"},"inheritGroupId":true,"groupId":"","isEntries":"false","recursiveSetEntries":true,"isPackInBuildIn":"false"},"ver":"1","size":216,"srcHash":"078c2a9b6c311d83623cbec08a369783","hash":"a034fcf28da9217e769dbe5c79bf7a78","dependencies":[],"fileDependencies":[],"service":"processService"}}},"60":{"60ac2fR-4fc9a5E-e1da69S-b05568R":{"path":"__temp/buildOnlyScriptProcess/typeScriptProcess/Scripts/Databus.js","tempPath":"","meta":{"uuid":"60ac2fR-4fc9a5E-e1da69S-b05568R","importSettings":{"processer":{"processVersion":"v2","fromLast":["60ac2fR-4fc9a5E-e1da69S-b05568R"],"fromSrc":["60ac2fR-4fc9a5E-e1da69S-b05568R"],"relatedSrcUuid":"60ac2fR-4fc9a5E-e1da69S-b05568R","ideDisplayAssetPath":"Scripts/Databus.ts","tempPath":"","loaderPath":"Scripts/Databus.ts","processName":"typeScriptProcess"},"inheritGroupId":true,"groupId":"","isEntries":"false","recursiveSetEntries":true,"isPackInBuildIn":"false"},"ver":"1","size":104,"srcHash":"8d927f9d155dcac7184740b66b843099","hash":"8cfe0515547e71ad4678b300a0f97141","dependencies":[],"fileDependencies":[],"service":"processService"}}},"61":{"614accR-a4e877E-02be6dS-49ed8fR":{"path":"__temp/buildOnlyScriptProcess/typeScriptProcess/Scripts/MyHandCard.js","tempPath":"","meta":{"uuid":"614accR-a4e877E-02be6dS-49ed8fR","importSettings":{"processer":{"processVersion":"v2","fromLast":["614accR-a4e877E-02be6dS-49ed8fR"],"fromSrc":["614accR-a4e877E-02be6dS-49ed8fR"],"relatedSrcUuid":"614accR-a4e877E-02be6dS-49ed8fR","ideDisplayAssetPath":"Scripts/MyHandCard.ts","tempPath":"","loaderPath":"Scripts/MyHandCard.ts","processName":"typeScriptProcess"},"inheritGroupId":true,"groupId":"","isEntries":"false","recursiveSetEntries":true,"isPackInBuildIn":"false"},"ver":"1","size":946,"srcHash":"cc2438697fb6573044bfaa543459249e","hash":"3894747f53a344b2c16acad137f98400","dependencies":[],"fileDependencies":[],"service":"processService"}}},"78":{"78caa5R-ed55c1E-48ada1S-26362dR":{"path":"__temp/buildOnlyScriptProcess/typeScriptProcess/Scripts/GameManager.js","tempPath":"","meta":{"uuid":"78caa5R-ed55c1E-48ada1S-26362dR","importSettings":{"processer":{"processVersion":"v2","fromLast":["78caa5R-ed55c1E-48ada1S-26362dR"],"fromSrc":["78caa5R-ed55c1E-48ada1S-26362dR"],"relatedSrcUuid":"78caa5R-ed55c1E-48ada1S-26362dR","ideDisplayAssetPath":"Scripts/GameManager.ts","tempPath":"","loaderPath":"Scripts/GameManager.ts","processName":"typeScriptProcess"},"inheritGroupId":true,"groupId":"","isEntries":"false","recursiveSetEntries":true,"isPackInBuildIn":"false"},"ver":"1","size":6070,"srcHash":"5b25b62c600493f9ddf8f11ff1cb5964","hash":"18c632b671943e90aad1e6029c9484dc","dependencies":[],"fileDependencies":[],"service":"processService"}}},"85":{"85b745R-645628E-dacec4S-2de877R":{"path":"__temp/buildOnlyScriptProcess/typeScriptProcess/.buildin/Editor/tutorial/skybox-criterion.js","tempPath":"","meta":{"uuid":"85b745R-645628E-dacec4S-2de877R","importSettings":{"processer":{"processVersion":"v2","fromLast":["85b745R-645628E-dacec4S-2de877R"],"fromSrc":["85b745R-645628E-dacec4S-2de877R"],"relatedSrcUuid":"85b745R-645628E-dacec4S-2de877R","ideDisplayAssetPath":".buildin/Editor/tutorial/skybox-criterion.ts","tempPath":"","loaderPath":".buildin/Editor/tutorial/skybox-criterion.ts","processName":"typeScriptProcess"},"inheritGroupId":true,"groupId":"","isEntries":"false","recursiveSetEntries":true,"isPackInBuildIn":"false"},"ver":"1","size":143,"srcHash":"ba8548d6b28c939721cc3f7549c4607b","hash":"5585ffab83964860e367795e07959231","dependencies":[],"fileDependencies":[],"service":"processService"}}},"cf":{"cff9dfR-04b842E-5fa5a7S-e58cabR":{"path":"__temp/buildOnlyScriptProcess/typeScriptProcess/.buildin/Editor/loadingScene/script/retryBtn.js","tempPath":"","meta":{"uuid":"cff9dfR-04b842E-5fa5a7S-e58cabR","importSettings":{"processer":{"processVersion":"v2","fromLast":["cff9dfR-04b842E-5fa5a7S-e58cabR"],"fromSrc":["cff9dfR-04b842E-5fa5a7S-e58cabR"],"relatedSrcUuid":"cff9dfR-04b842E-5fa5a7S-e58cabR","ideDisplayAssetPath":".buildin/Editor/loadingScene/script/retryBtn.ts","tempPath":"","loaderPath":".buildin/Editor/loadingScene/script/retryBtn.ts","processName":"typeScriptProcess"},"inheritGroupId":true,"groupId":"","isEntries":"false","recursiveSetEntries":true,"isPackInBuildIn":"false"},"ver":"1","size":626,"srcHash":"8d07b419ad1c6a2a9826de69640d6da6","hash":"30fe19853185aa2fb8a46b507681837d","dependencies":[],"fileDependencies":[],"service":"processService"}}},"db":{"dbfdfdR-5a8578E-a92a80S-252951R":{"path":"__temp/buildOnlyScriptProcess/typeScriptProcess/.buildin/Editor/loadingScene/common/Utils.js","tempPath":"","meta":{"uuid":"dbfdfdR-5a8578E-a92a80S-252951R","importSettings":{"processer":{"processVersion":"v2","fromLast":["dbfdfdR-5a8578E-a92a80S-252951R"],"fromSrc":["dbfdfdR-5a8578E-a92a80S-252951R"],"relatedSrcUuid":"dbfdfdR-5a8578E-a92a80S-252951R","ideDisplayAssetPath":".buildin/Editor/loadingScene/common/Utils.ts","tempPath":"","loaderPath":".buildin/Editor/loadingScene/common/Utils.ts","processName":"typeScriptProcess"},"inheritGroupId":true,"groupId":"","isEntries":"false","recursiveSetEntries":true,"isPackInBuildIn":"false"},"ver":"1","size":983,"srcHash":"b010c4343c38a388bc244923fe00efd5","hash":"da2724e51a357e466b5efc8627cd413b","dependencies":[],"fileDependencies":[],"service":"processService"}}},"4a":{"4af073R-ad6d32E-af94d6S-72830eR":{"path":"__temp/buildOnlyScriptProcess/typeScriptProcess/Scripts/utils.js","tempPath":"","meta":{"uuid":"4af073R-ad6d32E-af94d6S-72830eR","importSettings":{"processer":{"processVersion":"v2","fromLast":["4af073R-ad6d32E-af94d6S-72830eR"],"fromSrc":["4af073R-ad6d32E-af94d6S-72830eR"],"relatedSrcUuid":"4af073R-ad6d32E-af94d6S-72830eR","ideDisplayAssetPath":"Scripts/utils.ts","tempPath":"","loaderPath":"Scripts/utils.ts","processName":"typeScriptProcess"},"inheritGroupId":true,"groupId":"","isEntries":"false","recursiveSetEntries":true,"isPackInBuildIn":"false"},"ver":"1","size":957,"srcHash":"2e4e020bbe671459f24a4846cf3fafa4","hash":"3eedae2eb5b6bf146df183fef3461249","dependencies":[],"fileDependencies":[],"service":"processService"}}},"e7":{"e74694R-6f4f7dE-f12ae0S-007123R":{"path":"__temp/buildOnlyScriptProcess/typeScriptProcess/.buildin/Editor/defaultAssets/scriptableasset.js","tempPath":"","meta":{"uuid":"e74694R-6f4f7dE-f12ae0S-007123R","importSettings":{"processer":{"processVersion":"v2","fromLast":["e74694R-6f4f7dE-f12ae0S-007123R"],"fromSrc":["e74694R-6f4f7dE-f12ae0S-007123R"],"relatedSrcUuid":"e74694R-6f4f7dE-f12ae0S-007123R","ideDisplayAssetPath":".buildin/Editor/defaultAssets/scriptableasset.ts","tempPath":"","loaderPath":".buildin/Editor/defaultAssets/scriptableasset.ts","processName":"typeScriptProcess"},"inheritGroupId":true,"groupId":"","isEntries":"false","recursiveSetEntries":true,"isPackInBuildIn":"false"},"ver":"1","size":216,"srcHash":"ca5e885cacda7187cfd72c71d0041f78","hash":"e2c349f4825ac68ef98d343136aec477","dependencies":[],"fileDependencies":[],"service":"processService"}}},"07":{"070b6bR-cefe4fE-2a0cddS-01907dR":{"path":"__temp/buildOnlyScriptProcess/typeScriptProcess/.buildin/Editor/tutorial/default-tutorial-hooks.js","tempPath":"","meta":{"uuid":"070b6bR-cefe4fE-2a0cddS-01907dR","importSettings":{"processer":{"processVersion":"v2","fromLast":["070b6bR-cefe4fE-2a0cddS-01907dR"],"fromSrc":["070b6bR-cefe4fE-2a0cddS-01907dR"],"relatedSrcUuid":"070b6bR-cefe4fE-2a0cddS-01907dR","ideDisplayAssetPath":".buildin/Editor/tutorial/default-tutorial-hooks.ts","tempPath":"","loaderPath":".buildin/Editor/tutorial/default-tutorial-hooks.ts","processName":"typeScriptProcess"},"inheritGroupId":true,"groupId":"","isEntries":"false","recursiveSetEntries":true,"isPackInBuildIn":"false"},"ver":"1","size":443,"srcHash":"b7ab338c98fa411ce5590d33b42e442f","hash":"75c904f55853e4de2e1108c92199de5a","dependencies":[],"fileDependencies":[],"service":"processService"}}},"b8":{"b837a2R-14ea59E-dcf6d6S-f416f0R":{"path":"__temp/buildOnlyScriptProcess/typeScriptProcess/Scripts/CreateRoom.js","tempPath":"","meta":{"uuid":"b837a2R-14ea59E-dcf6d6S-f416f0R","importSettings":{"processer":{"processVersion":"v2","fromLast":["b837a2R-14ea59E-dcf6d6S-f416f0R"],"fromSrc":["b837a2R-14ea59E-dcf6d6S-f416f0R"],"relatedSrcUuid":"b837a2R-14ea59E-dcf6d6S-f416f0R","ideDisplayAssetPath":"Scripts/CreateRoom.ts","tempPath":"","loaderPath":"Scripts/CreateRoom.ts","processName":"typeScriptProcess"},"inheritGroupId":true,"groupId":"","isEntries":"false","recursiveSetEntries":true,"isPackInBuildIn":"false"},"ver":"1","size":321,"srcHash":"312467bafba34274c436c32fb4669ba1","hash":"da6beaa3476eb86e05a37e14341e2385","dependencies":[],"fileDependencies":[],"service":"processService"}}},"a3":{"a3849cR-582efeE-be8a78S-d06846R":{"path":"__temp/buildOnlyScriptProcess/typeScriptProcess/.buildin/Editor/loadingScene/progressbar/scripts/UIProgressBar.js","tempPath":"","meta":{"uuid":"a3849cR-582efeE-be8a78S-d06846R","importSettings":{"processer":{"processVersion":"v2","fromLast":["a3849cR-582efeE-be8a78S-d06846R"],"fromSrc":["a3849cR-582efeE-be8a78S-d06846R"],"relatedSrcUuid":"a3849cR-582efeE-be8a78S-d06846R","ideDisplayAssetPath":".buildin/Editor/loadingScene/progressbar/scripts/UIProgressBar.ts","tempPath":"","loaderPath":".buildin/Editor/loadingScene/progressbar/scripts/UIProgressBar.ts","processName":"typeScriptProcess"},"inheritGroupId":true,"groupId":"","isEntries":"false","recursiveSetEntries":true,"isPackInBuildIn":"false"},"ver":"1","size":2648,"srcHash":"a39068f8de9bf7fdb47df5512db5f0c3","hash":"734076519d90b9ba5c32ef9fef176456","dependencies":[],"fileDependencies":[],"service":"processService"}}},"cd":{"cdfea4R-c0c89aE-af208bS-901661R":{"path":"__temp/buildOnlyScriptProcess/typeScriptProcess/Scripts/GameServer.js","tempPath":"","meta":{"uuid":"cdfea4R-c0c89aE-af208bS-901661R","importSettings":{"processer":{"processVersion":"v2","fromLast":["cdfea4R-c0c89aE-af208bS-901661R"],"fromSrc":["cdfea4R-c0c89aE-af208bS-901661R"],"relatedSrcUuid":"cdfea4R-c0c89aE-af208bS-901661R","ideDisplayAssetPath":"Scripts/GameServer.ts","tempPath":"","loaderPath":"Scripts/GameServer.ts","processName":"typeScriptProcess"},"inheritGroupId":true,"groupId":"","isEntries":"false","recursiveSetEntries":true,"isPackInBuildIn":"false"},"ver":"1","size":718,"srcHash":"147a055960f6609bbf1e4c47d4f9a6b8","hash":"f3b91bef9d7b1a8bf6289fcf4a19d7b0","dependencies":[],"fileDependencies":[],"service":"processService"}}},"d5":{"d5edb2R-248ce6E-ba1f22S-3c93ffR":{"path":"__temp/buildOnlyScriptProcess/typeScriptProcess/Scripts/ExitRoom.js","tempPath":"","meta":{"uuid":"d5edb2R-248ce6E-ba1f22S-3c93ffR","importSettings":{"processer":{"processVersion":"v2","fromLast":["d5edb2R-248ce6E-ba1f22S-3c93ffR"],"fromSrc":["d5edb2R-248ce6E-ba1f22S-3c93ffR"],"relatedSrcUuid":"d5edb2R-248ce6E-ba1f22S-3c93ffR","ideDisplayAssetPath":"Scripts/ExitRoom.ts","tempPath":"","loaderPath":"Scripts/ExitRoom.ts","processName":"typeScriptProcess"},"inheritGroupId":true,"groupId":"","isEntries":"false","recursiveSetEntries":true,"isPackInBuildIn":"false"},"ver":"1","size":317,"srcHash":"c889b62d73b1ac837f54737da4b9e198","hash":"a75e82b19e8e2a6d3a94ecb85b39dab6","dependencies":[],"fileDependencies":[],"service":"processService"}}},"c7":{"c727dcR-10847dE-3538a9S-34d4e4R":{"path":"__temp/buildOnlyScriptProcess/typeScriptProcess/Scripts/Me.js","tempPath":"","meta":{"uuid":"c727dcR-10847dE-3538a9S-34d4e4R","importSettings":{"processer":{"processVersion":"v2","fromLast":["c727dcR-10847dE-3538a9S-34d4e4R"],"fromSrc":["c727dcR-10847dE-3538a9S-34d4e4R"],"relatedSrcUuid":"c727dcR-10847dE-3538a9S-34d4e4R","ideDisplayAssetPath":"Scripts/Me.ts","tempPath":"","loaderPath":"Scripts/Me.ts","processName":"typeScriptProcess"},"inheritGroupId":true,"groupId":"","isEntries":"false","recursiveSetEntries":true,"isPackInBuildIn":"false"},"ver":"1","size":313,"srcHash":"2fabed9e161fd4d5bc44dcba6dff9aed","hash":"c5f97d0729185153fdbbf8851de83e59","dependencies":[],"fileDependencies":[],"service":"processService"}}},"fd":{"fd35d9R-80dc0eE-a3b98fS-20c738R":{"path":"__temp/buildOnlyScriptProcess/typeScriptProcess/Scripts/Roommate.js","tempPath":"","meta":{"uuid":"fd35d9R-80dc0eE-a3b98fS-20c738R","importSettings":{"processer":{"processVersion":"v2","fromLast":["fd35d9R-80dc0eE-a3b98fS-20c738R"],"fromSrc":["fd35d9R-80dc0eE-a3b98fS-20c738R"],"relatedSrcUuid":"fd35d9R-80dc0eE-a3b98fS-20c738R","ideDisplayAssetPath":"Scripts/Roommate.ts","tempPath":"","loaderPath":"Scripts/Roommate.ts","processName":"typeScriptProcess"},"inheritGroupId":true,"groupId":"","isEntries":"false","recursiveSetEntries":true,"isPackInBuildIn":"false"},"ver":"1","size":3309,"srcHash":"f4697465a5f7eea2eba15fbef6b087ba","hash":"07f536736abbd4b5a4aa2e0f54f10752","dependencies":[],"fileDependencies":[],"service":"processService"}}}}}